[
	{
		"regex":"^(?:(?:(?:0?[13578]|1[02])(\\/|-|\\.)31)\\1|(?:(?:0?[13-9]|1[0-2])(\\/|-|\\.)(?:29|30)\\2))(?:(?:1[6-9]|[2-9]\\d)?\\d{2})$|^(?:0?2(\\/|-|\\.)29\\3(?:(?:(?:1[6-9]|[2-9]\\d)?(?:0[48]|[2468][048]|[13579][26])|(?:(?:16|[2468][048]|[3579][26])00))))$|^(?:(?:0?[1-9])|(?:1[0-2]))(\\/|-|\\.)(?:0?[1-9]|1\\d|2[0-8])\\4(?:(?:1[6-9]|[2-9]\\d)?\\d{2})$",
		"case":[
			"01.1.02",
			"11-30-2001",
			"2/29/2000"
		]
	},
	{
		"regex":"^\\$(\\d{1,3}(\\,\\d{3})*|(\\d+))(\\.\\d{2})?$",
		"case":[
			"$1,234,567.89",
			"$123458",
			"$0.84"
		]
	},
	{
		"regex":"(?i:(?=[MDCLXVI])((M{0,3})((C[DM])|(D?C{0,3}))?((X[LC])|(L?XX{0,2})|L)?((I[VX])|(V?(II{0,2}))|V)?))$",
		"case":[
			"xiv",
			"MCMXCIX",
			"III"
		]
	},
	{
		"regex":"^(([a-zA-Z]:)|(\\\\{2}\\w+)\\$?)(\\\\(\\w[\\w ]*))+\\.(txt|TXT)$",
		"case":[
			"c:\\folder\\sub folder\\file.txt",
			"c:\\file.txt",
			"\\\\network\\folder\\file.txt"
		]
	},
	{
		"regex":"^(?:(?:(?:(?:(?:1[6-9]|[2-9]\\d)?(?:0[48]|[2468][048]|[13579][26])|(?:(?:16|[2468][048]|[3579][26])00)))(\\/|-|\\.)(?:0?2\\1(?:29)))|(?:(?:(?:1[6-9]|[2-9]\\d)?\\d{2})(\\/|-|\\.)(?:(?:(?:0?[13578]|1[02])\\2(?:31))|(?:(?:0?[1,3-9]|1[0-2])\\2(29|30))|(?:(?:0?[1-9])|(?:1[0-2]))\\2(?:0?[1-9]|1\\d|2[0-8]))))$",
		"case":[
			"2002-4-30",
			"04/2/29",
			"04/2/29"
		]
	},
	{
		"regex":"^(?=\\d)(?:(?:(?:(?:(?:0?[13578]|1[02])(\\/|-|\\.)31)\\1|(?:(?:0?[1,3-9]|1[0-2])(\\/|-|\\.)(?:29|30)\\2))(?:(?:1[6-9]|[2-9]\\d)?\\d{2})|(?:0?2(\\/|-|\\.)29\\3(?:(?:(?:1[6-9]|[2-9]\\d)?(?:0[48]|[2468][048]|[13579][26])|(?:(?:16|[2468][048]|[3579][26])00))))|(?:(?:0?[1-9])|(?:1[0-2]))(\\/|-|\\.)(?:0?[1-9]|1\\d|2[0-8])\\4(?:(?:1[6-9]|[2-9]\\d)?\\d{2}))($|\\ (?=\\d)))?(((0?[1-9]|1[012])(:[0-5]\\d){0,2}(\\ [AP]M))|([01]\\d|2[0-3])(:[0-5]\\d){1,2})?$",
		"case":[
			"12/25/2003",
			"08:03:31",
			"02/29/2004 12 AM"
		]
	},
	{
		"regex":"^((0?[1-9]|1[012])(:[0-5]\\d){0,2}(\\ [AP]M))$|^([01]\\d|2[0-3])(:[0-5]\\d){0,2}$",
		"case":[
			"1 AM",
			"23:00:00",
			"5:29:59 PM"
		]
	},
	{
		"regex":"^(Sun|Mon|(T(ues|hurs))|Fri)(day|\\.)?$|Wed(\\.|nesday)?$|Sat(\\.|urday)?$|T((ue?)|(hu?r?))\\.?$",
		"case":[
			"Sunday",
			"Mon",
			"Tu"
		]
	},
	{
		"regex":"^(?:(((Jan(uary)?|Ma(r(ch)?|y)|Jul(y)?|Aug(ust)?|Oct(ober)?|Dec(ember)?)\\ 31)|((Jan(uary)?|Ma(r(ch)?|y)|Apr(il)?|Ju((ly?)|(ne?))|Aug(ust)?|Oct(ober)?|(Sept|Nov|Dec)(ember)?)\\ (0?[1-9]|([12]\\d)|30))|(Feb(ruary)?\\ (0?[1-9]|1\\d|2[0-8]|(29(?=,\\ ((1[6-9]|[2-9]\\d)(0[48]|[2468][048]|[13579][26])|((16|[2468][048]|[3579][26])00)))))))\\,\\ ((1[6-9]|[2-9]\\d)\\d{2}))",
		"case":[
			"Jan 1, 2003",
			"February 29, 2004",
			"November 02, 3202"
		]
	},
	{
		"regex":"^(?:J(anuary|u(ne|ly))|February|Ma(rch|y)|A(pril|ugust)|(((Sept|Nov|Dec)em)|Octo)ber)$",
		"case":[
			"January",
			"May",
			"October"
		]
	},
	{
		"regex":"<(\\w+)(\\s(\\w*=\".*?\")?)*((/>)|((/*?)>.*?</\\1>))",
		"case":[
			"<body> text<br/>More Text </body>"
		]
	},
	{
		"regex":"ISBN\\x20(?=.{13}$)\\d{1,5}([- ])\\d{1,7}\\1\\d{1,6}\\1(\\d|X)$",
		"case":[
			"ISBN 1-56389-016-X",
			"ISBN 0 93028 923 4"
		]
	},
	{
		"regex":"^(?-i:A[LKSZRAEP]|C[AOT]|D[EC]|F[LM]|G[AU]|HI|I[ADLN]|K[SY]|LA|M[ADEHINOPST]|N[CDEHJMVY]|O[HKR]|P[ARW]|RI|S[CD]|T[NX]|UT|V[AIT]|W[AIVY])$",
		"case":[
			"AA",
			"AL",
			"CA"
		]
	},
	{
		"regex":"^(?:(?<lastname>(St\\.\\ )?(?-i:[A-Z]\\'?\\w+?\\-?)+)(?<suffix>\\ (?i:([JS]R)|((X(X{1,2})?)?((I((I{1,2})|V|X)?)|(V(I{0,3})))?)))?,((?<prefix>Dr|Prof|M(r?|(is)?)s)\\ )?(?<firstname>(?-i:[A-Z]\\'?(\\w+?|\\.)\\ ??){1,2})?(\\ (?<mname>(?-i:[A-Z])(\\'?\\w+?|\\.))){0,2})$",
		"case":[
			"O'Brien, Miles",
			"McDonald,Mary Ann Alison",
			"Windsor-Smith,Barry"
		]
	},
	{
		"regex":"(<\\/?)(?i:(?<element>a(bbr|cronym|ddress|pplet|rea)?|b(ase(font)?|do|ig|lockquote|ody|r|utton)?|c(aption|enter|ite|(o(de|l(group)?)))|d(d|el|fn|i(r|v)|l|t)|em|f(ieldset|o(nt|rm)|rame(set)?)|h([1-6]|ead|r|tml)|i(frame|mg|n(put|s)|sindex)?|kbd|l(abel|egend|i(nk)?)|m(ap|e(nu|ta))|no(frames|script)|o(bject|l|pt(group|ion))|p(aram|re)?|q|s(amp|cript|elect|mall|pan|t(r(ike|ong)|yle)|u(b|p))|t(able|body|d|extarea|foot|h|itle|r|t)|u(l)?|var))(\\s(?<attr>.+?))*>",
		"case":[
			"<HTML>",
			"<a href=\"link.html\">Link</a>"
		]
	},
	{
		"regex":"(?i:on(blur|c(hange|lick)|dblclick|focus|keypress|(key|mouse)(down|up)|(un)?load|mouse(move|o(ut|ver))|reset|s(elect|ubmit)))",
		"case":[
			"onclick",
			"onsubmit",
			"onmouseover"
		]
	},
	{
		"regex":"^(?!000)([0-6]\\d{2}|7([0-6]\\d|7[012]))([ -]?)(?!00)\\d\\d\\3(?!0000)\\d{4}$",
		"case":[
			"078-05-1120",
			"078 05 1120",
			"078051120"
		]
	},
	{
		"regex":"(?i:([A-D])(?!\\1)([A-D])(?!\\1|\\2)([A-D])(?!\\1|\\2|\\3)([A-D]))",
		"case":[
			"abcd",
			"dbca",
			"badc"
		]
	},
	{
		"regex":"^(?=[^\\d_].*?\\d)\\w(\\w|[!@#$%]){7,20}",
		"case":[
			"password1",
			"pa$$word2",
			"pa$$word2"
		]
	},
	{
		"regex":"^(?=\\d)(?:(?:31(?!.(?:0?[2469]|11))|(?:30|29)(?!.0?2)|29(?=.0?2.(?:(?:(?:1[6-9]|[2-9]\\d)?(?:0[48]|[2468][048]|[13579][26])|(?:(?:16|[2468][048]|[3579][26])00)))(?:\\x20|$))|(?:2[0-8]|1\\d|0?[1-9]))([-./])(?:1[012]|0?[1-9])\\1(?:1[6-9]|[2-9]\\d)?\\d\\d(?:(?=\\x20\\d)\\x20|$))?(((0?[1-9]|1[012])(:[0-5]\\d){0,2}(\\x20[AP]M))|([01]\\d|2[0-3])(:[0-5]\\d){1,2})?$",
		"case":[
			"31/12/2003 11:59:59 PM",
			"29-2-2004",
			"01:45:02"
		]
	},
	{
		"regex":"^(\\x22|\\x27)((?!\\1).|\\1{2})*\\1$",
		"case":[
			"\"To quote Yoda (\"\"Do, or do not. There is no 'try'\"\" )\""
		]
	},
	{
		"regex":"(?=\\d)^(?:(?!(?:10\\D(?:0?[5-9]|1[0-4])\\D(?:1582))|(?:0?9\\D(?:0?[3-9]|1[0-3])\\D(?:1752)))((?:0?[13578]|1[02])|(?:0?[469]|11)(?!\\/31)(?!-31)(?!\\.31)|(?:0?2(?=.?(?:(?:29.(?!000[04]|(?:(?:1[^0-6]|[2468][^048]|[3579][^26])00))(?:(?:(?:\\d\\d)(?:[02468][048]|[13579][26])(?!\\x20BC))|(?:00(?:42|3[0369]|2[147]|1[258]|09)\\x20BC))))))|(?:0?2(?=.(?:(?:\\d\\D)|(?:[01]\\d)|(?:2[0-8])))))([-.\\/])(0?[1-9]|[12]\\d|3[01])\\2(?!0000)((?=(?:00(?:4[0-5]|[0-3]?\\d)\\x20BC)|(?:\\d{4}(?!\\x20BC)))\\d{4}(?:\\x20BC)?)(?:$|(?=\\x20\\d)\\x20))?((?:(?:0?[1-9]|1[012])(?::[0-5]\\d){0,2}(?:\\x20[aApP][mM]))|(?:[01]\\d|2[0-3])(?::[0-5]\\d){1,2})?$",
		"case":[
			"11/24/0004 11:59 PM",
			"2.29.2008",
			"02:50:10"
		]
	},
	{
		"regex":"^((?:[a-zA-Z]:)|(?:\\\\{2}\\w[-\\w]*)\\$?)\\\\(?!\\.)((?:(?![\\\\/:*?<>\"|])(?![.\\x20](?:\\\\|$))[\\x20-\\x7E])+\\\\(?!\\.))*((?:(?:(?![\\\\/:*?<>\"|])(?![ .]$)[\\x20-\\x7E])+)\\.((?:(?![\\\\/:*?<>\"|])(?![ .]$)[\\x20-\\x7E]){2,15}))?$",
		"case":[
			"C:\\",
			"\\\\Server\\share\\path\\File.txt",
			"E:\\My Files\\Are\\#1\\"
		]
	},
	{
		"regex":"\\b-?[1-9](?:\\.\\d+)?[Ee][-+]?\\d+\\b",
		"case":[
			"9.4608e15",
			"3.7E-11"
		]
	},
	{
		"regex":"ISBN(?:-13)?:?\\x20*(?=.{17}$)97(?:8|9)([ -])\\d{1,5}\\1\\d{1,7}\\1\\d{1,6}\\1\\d$",
		"case":[
			"ISBN-13: 978-1-4028-9462-6"
		]
	},
	{
		"regex":"^((4\\d{3})|(5[1-5]\\d{2})|(6011))-?\\d{4}-?\\d{4}-?\\d{4}|3[4,7]\\d{13}$",
		"case":[
			"6011-1111-1111-1111",
			"5423-1111-1111-1111",
			"341111111111111"
		]
	},
	{
		"regex":"^(20|21|22|23|[0-1]\\d)[0-5]\\d$",
		"case":[
			"1200",
			"1645",
			"2359"
		]
	},
	{
		"regex":".*(\\.[Jj][Pp][Gg]|\\.[Gg][Ii][Ff]|\\.[Jj][Pp][Ee][Gg]|\\.[Pp][Nn][Gg])",
		"case":[
			"foo.gif",
			"foo.jpg",
			"foo.png"
		]
	},
	{
		"regex":"^[a-zA-Z0-9!#$%&'*+/=?^_`{|}~-]+(?:\\.[a-zA-Z0-9!#$%&'*+/=?^_`{|}~-]+)*@(?:[a-zA-Z0-9](?:[a-zA-Z0-9-]*[a-zA-Z0-9])?\\.)+(?:[a-zA-Z]{2}|aero|asia|biz|cat|com|coop|edu|gov|info|int|jobs|mil|mobi|museum|name|net|org|pro|tel|travel)$",
		"case":[
			"email@email.com",
			"email@email.cn",
			"e_m81l&em%'l@eMail.MUSEUM",
			"email@em@il.com"
		]
	},
	{
		"regex":"^([+][0-9]{1,3}([ .\\-])?)?([(][0-9]{3}[)])?([0-9A-Z .\\-]{1,32})((x|ext|extension)?[0-9]{1,4}?)$",
		"case":[
			"(123)456-7890",
			"(123)456-7890 x123",
			"+1 (123)456-7890",
			"12 3456 789 0 x1234",
			"(123)456-7890x123",
			"+12 34 56 7890"
		]
	},
	{
		"regex":"^(?i)(-?[1-9](\\.\\d+)?)((\\s?[X*]\\s?10[E^]([+-]?\\d+))|(E([+-]?\\d+)))$",
		"case":[
			"-2.34 X 10E12",
			"-3.14159 * 10e30",
			"2.34 X 10^12"
		]
	},
	{
		"regex":"^(?:(?:^|,\\s*)([01]?\\d\\d?|2[0-4]\\d|25[0-5])){3}$",
		"case":[
			"120,155,0",
			"0,0,0",
			"254,244,008"
		]
	},
	{
		"regex":"([\\d\\w-.]+?\\.(a[cdefgilmnoqrstuwz]|b[abdefghijmnorstvwyz]|c[acdfghiklmnoruvxyz]|d[ejkmnoz]|e[ceghrst]|f[ijkmnor]|g[abdefghilmnpqrstuwy]|h[kmnrtu]|i[delmnoqrst]|j[emop]|k[eghimnprwyz]|l[abcikrstuvy]|m[acdghklmnopqrstuvwxyz]|n[acefgilopruz]|om|p[aefghklmnrstwy]|qa|r[eouw]|s[abcdeghijklmnortuvyz]|t[cdfghjkmnoprtvwz]|u[augkmsyz]|v[aceginu]|w[fs]|y[etu]|z[amw]|aero|arpa|biz|com|coop|edu|info|int|gov|mil|museum|name|net|org|pro)(\\b|\\W(?<!&|=)(?!\\.\\s|\\.{3}).*?))(\\s|$)",
		"case":[
			"www.website.com",
			"website.com"
		]
	},
	{
		"regex":"((978[\\--– ])?[0-9][0-9\\--– ]{10}[\\--– ][0-9xX])|((978)?[0-9]{9}[0-9Xx])",
		"case":[
			"978-1-4302-1998-9",
			"978-0-07-162612-5",
			"0 321 15420 7"
		]
	},
	{
		"regex":"[一-龥]",
		"case":[
			"你",
			"我"
		]
	},
	{
		"regex":"(?:(?!0000)[0-9]{4}-(?:(?:0[1-9]|1[0-2])-(?:0[1-9]|1[0-9]|2[0-8])|(?:0[13-9]|1[0-2])-(?:29|30)|(?:0[13578]|1[02])-31)|(?:[0-9]{2}(?:0[48]|[2468][048]|[13579][26])|(?:0[48]|[2468][048]|[13579][26])00)-02-29)",
		"case":[
			"2022-06-30",
			"2025-04-30"
		]
	},
	{
		"regex":"((?:25[0-5]|2[0-4][0-9]|[01]?[0-9][0-9]?)\\.){3}(?:25[0-5]|2[0-4][0-9]|[01]?[0-9][0-9]?)",
		"case":[
			"01.01.01.01",
			"255.255.255.255"
		]
	},
	{
		"regex":"(([0-9a-fA-F]{1,4}:){7,7}[0-9a-fA-F]{1,4}|([0-9a-fA-F]{1,4}:){1,7}:|([0-9a-fA-F]{1,4}:){1,6}:[0-9a-fA-F]{1,4}|([0-9a-fA-F]{1,4}:){1,5}(:[0-9a-fA-F]{1,4}){1,2}|([0-9a-fA-F]{1,4}:){1,4}(:[0-9a-fA-F]{1,4}){1,3}|([0-9a-fA-F]{1,4}:){1,3}(:[0-9a-fA-F]{1,4}){1,4}|([0-9a-fA-F]{1,4}:){1,2}(:[0-9a-fA-F]{1,4}){1,5}|[0-9a-fA-F]{1,4}:((:[0-9a-fA-F]{1,4}){1,6})|:((:[0-9a-fA-F]{1,4}){1,7}|:)|fe80:(:[0-9a-fA-F]{0,4}){0,4}%[0-9a-zA-Z]{1,}|::(ffff(:0{1,4}){0,1}:){0,1}((25[0-5]|(2[0-4]|1{0,1}[0-9]){0,1}[0-9])\\.){3,3}(25[0-5]|(2[0-4]|1{0,1}[0-9]){0,1}[0-9])|([0-9a-fA-F]{1,4}:){1,4}:((25[0-5]|(2[0-4]|1{0,1}[0-9]){0,1}[0-9])\\.){3,3}(25[0-5]|(2[0-4]|1{0,1}[0-9]){0,1}[0-9]))",
		"case":[
			"2345:0425:2CA1:0000:0000:0567:5673:23b5"
		]
	},
	{
		"regex":"[\\w!#$%&'*+/=?^_`{|}~-]+(\\.[\\w!#$%&'*+/=?^_`{|}~-]+)*@([\\w]([\\w-]*[\\w])?\\.)+[\\w]([\\w-]*[\\w])?",
		"case":[
			"abc@qq.com"
		]
	},
	{
		"regex":"^(d{0}|(31(?!(FEB|APR|JUN|SEP|NOV)))|((30|29)(?!FEB))|(29(?=FEB(((1[6-9]|[2-9]\\d)(0[48]|[2468][048]|[13579][26])|((16|[2468][048]|[3579][26])00)))))|(29(?=FEB(((0[48]|[2468][048]|[13579][26])|((16|[2468][048]|[3579][26])00)))))|(0?[1-9])|1\\d|2[0-8])(JAN|FEB|MAR|MAY|APR|JUL|JUN|AUG|OCT|SEP|NOV|DEC)((1[6-9]|[2-9]\\d)\\d{2}|\\d{2}|d{0})$",
		"case":[
			"12MAR02",
			"12MAR2008",
			"29FEB2008"
		]
	},
	{
		"regex":"^(?=^.{1,254}$)(^(?:(?!\\.|-)([a-z0-9\\-\\*]{1,63}|([a-z0-9\\-]{1,62}[a-z0-9]))\\.)+(?:[a-z]{2,})$)$",
		"case":[
			"12.152.80.in-addr.arpa",
			"*.domain.de",
			"test.de"
		]
	},
	{
		"regex":"^\\s*[+-]?\\s*(?:\\d{1,3}(?:(,?)\\d{3})?(?:\\1\\d{3})*(\\.\\d*)?|\\.\\d+)\\s*$",
		"case":[
			"123.23"
		]
	},
	{
		"regex":"^(([a-zA-Z]:)|(\\\\{2}\\w+)\\$?)(\\\\(\\w[\\w ]*.*))+\\.((html|HTML)|(htm|HTM))$",
		"case":[
			"c:\\arquivo.htm",
			"\\\\home\\arquivo232.HTML",
			"Z:\\teste.htm"
		]
	},
	{
		"regex":"^[^'<>?%!\\s]{1,20}$",
		"case":[
			"abcd123",
			"-+abc"
		]
	},
	{
		"regex":"(?=^.{12,25}$)(?=(?:.*?\\d){2})(?=.*[a-z])(?=(?:.*?[A-Z]){2})(?=(?:.*?[!@#$%*()_+^&}{:;?.]){2})(?!.*\\s)[0-9a-zA-Z!@#$%*()_+^&]*$",
		"case":[
			"pAsSword@#123",
			"PassW0rd@1*3"
		]
	},
	{
		"regex":"(?=^.{1,}$)(?!.*\\s)[0-9a-zA-Z!@#$%*()_+^&\\[\\]]*$",
		"case":[
			"abc*()A123",
			"12xyz[_]"
		]
	},
	{
		"regex":"^(?:[\\w]\\:|\\\\)(\\\\[a-z_\\-\\s0-9\\.]+)+\\.(txt|gif|pdf|doc|docx|xls|xlsx)$",
		"case":[
			"\\\\192.168.0.1\\folder\\file.pdf",
			"\\\\192.168.0.1\\my folder\\folder.2\\file.gif",
			"c:\\my folder\\abc abc.docx"
		]
	},
	{
		"regex":"^(?=.*[0-9]+.*)(?=.*[a-zA-Z]+.*)[0-9a-zA-Z]{6,}$",
		"case":[
			"a1b2c3",
			"abcdefg123",
			"12345a"
		]
	},
	{
		"regex":"<script(?:(?:.*(?<src>(?<=src=\")[^\"]*(?=\"))[^>]*)|[^>]*)>(?<content>(?:(?:\\n|.)(?!(?:\\n|.)<script))*)</script>",
		"case":[
			"<script type=\"text/javascript\" src=\"Test.js\"></script>"
		]
	},
	{
		"regex":"([+]?\\d[ ]?[(]?\\d{3}[)]?[ ]?\\d{2,3}[- ]?\\d{2}[- ]?\\d{2})",
		"case":[
			"+7 (960) 000 00 00",
			"+7(4855)23-34-56",
			"88002345675"
		]
	},
	{
		"regex":"^[0-9]{6}-[0-9pPtTfF][0-9]{3}$",
		"case":[
			"123456-f234",
			"123456-P234",
			"123456-1234"
		]
	},
	{
		"regex":"^[A-Za-z]{1,2}[\\d]{1,2}([A-Za-z])?\\s?[\\d][A-Za-z]{2}$",
		"case":[
			"CF1 2AA",
			"cf564fg"
		]
	},
	{
		"regex":"^([0-2][0-9]\\:[0-5][0-9]\\:[0-5][0-9])\\s+up\\s+([0-9\\:]{1,5})\\s*(days|day|min|mins)?(?:\\,\\s+([0-9\\:]{1,5})\\s*(days|day|min|mins)?)?\\,\\s+([0-9]{1,4})\\susers?\\,\\s+load\\s+average\\:\\s+([0-9\\.]{1,6})\\,\\s+([0-9\\.]{1,6})\\,\\s+([0-9\\.]{1,6})$",
		"case":[
			"13:21:33 up 219 days, 1:11, 1 user, load average: 0.00, 0.00, 0.00",
			"21:17:21 up 19 days, 9:34, 1 user, load average: 0.00, 0.00, 0.00",
			"1:17:21 up 19 days, 9:34, 1 user, load average: 12.30, 5.02, 1.20"
		]
	},
	{
		"regex":"^(?=[^&])(?:(?<scheme>[^:/?#]+):)?(?://(?<authority>[^/?#]*))?(?<path>[^?#]*)(?:\\?(?<query>[^#]*))?(?:#(?<fragment>.*))?",
		"case":[
			"http://regexlib.com/REDetails.aspx?regexp_id=x#Details"
		]
	},
	{
		"regex":"\\b(([\\w-]+://?|www[.])[^\\s()<>]+(?:\\([\\w\\d]+\\)|([^! \"#$%&'()*+,\\-./:;<=>?@\\[\\]^_{|}~`\\s]|/)))",
		"case":[
			"http://foo.com/blah_blah",
			"http://foo.com/blah_blah/",
			"http://www.example.com/wpstyle/?p=364"
		]
	},
	{
		"regex":"^((\\+){0,1}91(\\s){0,1}(\\-){0,1}(\\s){0,1}){0,1}9[0-9](\\s){0,1}(\\-){0,1}(\\s){0,1}[1-9]{1}[0-9]{7}$",
		"case":[
			"+919836193498",
			"9836193498"
		]
	},
	{
		"regex":"^(\\d{4})(?:-([0]\\d|[1][0-2]))(?:-([0-2]\\d|[3][01]))(?:T([01]\\d|2[0-3]))(?::([0-5]\\d))(?::([0-5]\\d)(?:\\.(\\d{1,7}?)|)|)(Z|([+-])([01]\\d|2[0-3])(?::([0-5]\\d)))$",
		"case":[
			"2013-12-01T04:33Z",
			"2013-12-01T04:33:12.234Z",
			"2013-12-01T23:12-07:00"
		]
	},
	{
		"regex":"^(?:[2-9]\\d\\d\\d)-(?:1[012]|0?[1-9])?-(?:31(?!.(?:0?[2469]|11))|(?:30|29)(?!.0?2)|29(?=.0?2.(?:(?:(?:1[6-9]|[2-9]\\d)?(?:0[48]|[2468][048]|[13579][26])|(?:(?:16|[2468][048]|[3579][26])00)))(?:T))|(?:2[0-8]|1\\d|0?[1-9]))T(2[01234]|[01]\\d):[0-5]\\d:[0-5]\\d[+-][01]\\d:[0-5]\\d$",
		"case":[
			"2016-04-07T11:13:00-05:00",
			"2016-04-07T12:29:00-04:00",
			"2016-04-05T00:53:35-04:00"
		]
	}
]